adb_wifi_py/__init__.py
adb_wifi_py/__main__.py
adb_wifi_py/main.py
adb_wifi_py-0.3.1234.dist-info/METADATA
adb_wifi_py-0.3.1234.dist-info/WHEEL
adb_wifi_py-0.3.1234.dist-info/entry_points.txt
adb_wifi_py-0.3.1234.dist-info/licenses/LICENSE
adb_wifi_py-0.3.1234.dist-info/RECORD
