Metadata-Version: 2.4
Name: adb-wifi-py
Version: 0.3.1234
Summary: A tool for pairing Android 11 and newer devices for wireless debugging directly through a terminal using QR code.
Project-URL: Homepage, https://github.com/Vazgen005/adb-wifi-py
Project-URL: Issues, https://github.com/Vazgen005/adb-wifi-py/issues
License-File: LICENSE
Requires-Python: >=3.8
Requires-Dist: colorama>=0.4.6
Requires-Dist: qrcode>=8.0
Requires-Dist: zeroconf>=0.136.2
